CHANGES.rst
MANIFEST.in
README.rst
bootstrap.py
buildout.cfg
setup.py
collective/__init__.py
collective.iconifieddocumentactions.egg-info/PKG-INFO
collective.iconifieddocumentactions.egg-info/SOURCES.txt
collective.iconifieddocumentactions.egg-info/dependency_links.txt
collective.iconifieddocumentactions.egg-info/entry_points.txt
collective.iconifieddocumentactions.egg-info/namespace_packages.txt
collective.iconifieddocumentactions.egg-info/requires.txt
collective.iconifieddocumentactions.egg-info/top_level.txt
collective.iconifieddocumentactions.egg-info/zip-safe
collective/iconifieddocumentactions/__init__.py
collective/iconifieddocumentactions/configure.zcml
collective/iconifieddocumentactions/interfaces.py
collective/iconifieddocumentactions/testing.py
collective/iconifieddocumentactions/upgrades.py
collective/iconifieddocumentactions/browser/__init__.py
collective/iconifieddocumentactions/browser/configure.zcml
collective/iconifieddocumentactions/browser/iconified_document_actions.pt
collective/iconifieddocumentactions/browser/viewlets.py
collective/iconifieddocumentactions/profiles/default/browserlayer.xml
collective/iconifieddocumentactions/profiles/default/cssregistry.xml
collective/iconifieddocumentactions/profiles/default/metadata.xml
collective/iconifieddocumentactions/profiles/default/viewlets.xml
collective/iconifieddocumentactions/static/iconified_document_actions.css
collective/iconifieddocumentactions/tests/test_robot.py
collective/iconifieddocumentactions/tests/test_setup.py
collective/iconifieddocumentactions/tests/robot/test_icon.robot
docs/INSTALL.txt
docs/LICENSE.GPL
docs/LICENSE.txt