Metadata-Version: 2.1
Name: collective.iconifieddocumentactions
Version: 1.3.2
Summary: Display document_actions as icons
Home-page: https://github.com/IMIO/collective.iconifieddocumentactions
Author: Imio
Author-email: support@imio.be
License: GPL
Platform: UNKNOWN
Classifier: Programming Language :: Python
Classifier: Topic :: Software Development :: Libraries :: Python Modules
Provides-Extra: test
